certs/__init__.py
certs/capella_root_ca.pem
mcp_server.py
tools/__init__.py
tools/index.py
tools/kv.py
tools/query.py
tools/server.py
utils/__init__.py
utils/config.py
utils/connection.py
utils/constants.py
utils/context.py
utils/index_utils.py
couchbase_mcp_server-0.5.2.dist-info/METADATA
couchbase_mcp_server-0.5.2.dist-info/WHEEL
couchbase_mcp_server-0.5.2.dist-info/entry_points.txt
couchbase_mcp_server-0.5.2.dist-info/licenses/LICENSE
couchbase_mcp_server-0.5.2.dist-info/RECORD
