Metadata-Version: 2.4
Name: couchbase-mcp-server
Version: 0.5.2
Summary: Couchbase MCP Server - The Developer Data Platform for Critical Applications in Our AI World
Project-URL: Homepage, https://github.com/Couchbase-Ecosystem/mcp-server-couchbase
Project-URL: Documentation, https://github.com/Couchbase-Ecosystem/mcp-server-couchbase#readme
Project-URL: Issues, https://github.com/Couchbase-Ecosystem/mcp-server-couchbase/issues
Author-email: Nithish Raghunandanan <devadvocates@couchbase.com>
License-Expression: Apache-2.0
License-File: LICENSE
Classifier: Development Status :: 4 - Beta
Classifier: Programming Language :: Python :: 3
Classifier: Topic :: Database
Requires-Python: <3.14,>=3.10
Requires-Dist: click<9.0.0,>=8.2.1
Requires-Dist: couchbase<5.0.0,>=4.4.0
Requires-Dist: lark-sqlpp>=0.0.1
Requires-Dist: mcp[cli]<2.0.0,>=1.20.0
Requires-Dist: urllib3>=2.0.0
Provides-Extra: dev
Requires-Dist: pre-commit==4.2.0; extra == 'dev'
Requires-Dist: ruff==0.12.5; extra == 'dev'
